_ruamel_yaml.cpython-39-x86_64-linux-gnu.so
ruamel_yaml_clib-0.2.15.dist-info/METADATA
ruamel_yaml_clib-0.2.15.dist-info/WHEEL
ruamel_yaml_clib-0.2.15.dist-info/top_level.txt
ruamel_yaml_clib-0.2.15.dist-info/RECORD
ruamel_yaml_clib-0.2.15.dist-info/licenses/LICENSE
